{"name":"thegove_lorenzo-shipping-company","title":"Lorenzo Shipping Company","description":"Fictitious data to help students learn SQL\n\n---\n{\"editor\":\"simple\"}\n---\nThis data set is provided as a resource for instructors to use for in-class demonstrations as well as for students to explore using SQL. These data are of a fictional transporation company, Lorenzo Transit Corporation (LTC). Customers hire LTC to move goods from their location to a specified city. LTC uses 18-wheel tractor trailers and specializes in less-than-full loads. On each shipment, a particular driver uses a truck to make a delivery to the city specified by the customer.\n\n​\n\n![https://media.data.world/UYWCr1G8TTa0BaDHZAUq\\_LORENZO.png](https://media.data.world/UYWCr1G8TTa0BaDHZAUq_LORENZO.png)","homepage":"https://data.world/thegove/lorenzo-shipping-company","resources":[{"name":"city","schema":{"fields":[{"name":"city_id","title":"city_id","description":"Unique identifier for the city","type":"integer","rdfType":"http://www.w3.org/2001/XMLSchema#integer","dwSourceId":"city_id"},{"name":"city_name","title":"city_name","description":"Name of the city","type":"string","rdfType":"http://www.w3.org/2001/XMLSchema#string","dwSourceId":"city_name"},{"name":"state","title":"state","description":"State in which the city is","type":"string","rdfType":"http://www.w3.org/2001/XMLSchema#string","dwSourceId":"state"},{"name":"population","title":"population","description":"Population of the city","type":"integer","rdfType":"http://www.w3.org/2001/XMLSchema#integer","dwSourceId":"population"},{"name":"area","title":"area","description":"Square miles the city covers","type":"number","rdfType":"http://www.w3.org/2001/XMLSchema#decimal","dwSourceId":"area"}]},"path":"data/city.csv","format":"csv"},{"name":"customer","schema":{"fields":[{"name":"cust_id","title":"cust_id","description":"Unique identifier for the customer","type":"integer","rdfType":"http://www.w3.org/2001/XMLSchema#integer","dwSourceId":"cust_id"},{"name":"cust_name","title":"cust_name","description":"Business name of the customer","type":"string","rdfType":"http://www.w3.org/2001/XMLSchema#string","dwSourceId":"cust_name"},{"name":"annual_revenue","title":"annual_revenue","description":"Annual revenue of the customer","type":"integer","rdfType":"http://www.w3.org/2001/XMLSchema#integer","dwSourceId":"annual_revenue"},{"name":"cust_type","title":"cust_type","description":"Whether the customer is a manufacturer or a wholesaler","type":"string","rdfType":"http://www.w3.org/2001/XMLSchema#string","dwSourceId":"cust_type"},{"name":"address","title":"address","description":"Physical street address of the customer","type":"string","rdfType":"http://www.w3.org/2001/XMLSchema#string","dwSourceId":"address"},{"name":"city","title":"city","description":"City of the customer's address","type":"string","rdfType":"http://www.w3.org/2001/XMLSchema#string","dwSourceId":"city"},{"name":"state","title":"state","description":"State of the customer's address","type":"string","rdfType":"http://www.w3.org/2001/XMLSchema#string","dwSourceId":"state"},{"name":"zip","title":"zip","description":"Postal code of the customer's address","type":"integer","rdfType":"http://www.w3.org/2001/XMLSchema#integer","dwSourceId":"zip"},{"name":"phone","title":"phone","description":"Telephone number to reach the customer","type":"string","rdfType":"http://www.w3.org/2001/XMLSchema#string","dwSourceId":"phone"}]},"path":"data/customer.csv","format":"csv"},{"name":"driver","schema":{"fields":[{"name":"driver_id","title":"driver_id","description":"Unique identifier for the driver","type":"integer","rdfType":"http://www.w3.org/2001/XMLSchema#integer","dwSourceId":"driver_id"},{"name":"first_name","title":"first_name","description":"First given name of the driver","type":"string","rdfType":"http://www.w3.org/2001/XMLSchema#string","dwSourceId":"first_name"},{"name":"last_name","title":"last_name","description":"Family name of the driver","type":"string","rdfType":"http://www.w3.org/2001/XMLSchema#string","dwSourceId":"last_name"},{"name":"address","title":"address","description":"Street address of the driver's home","type":"string","rdfType":"http://www.w3.org/2001/XMLSchema#string","dwSourceId":"address"},{"name":"city","title":"city","description":"City the driver lives in","type":"string","rdfType":"http://www.w3.org/2001/XMLSchema#string","dwSourceId":"city"},{"name":"state","title":"state","description":"State the driver lives in","type":"string","rdfType":"http://www.w3.org/2001/XMLSchema#string","dwSourceId":"state"},{"name":"zip_code","title":"zip_code","description":"postal code of the driver's address","type":"integer","rdfType":"http://www.w3.org/2001/XMLSchema#integer","dwSourceId":"zip_code"},{"name":"phone","title":"phone","description":"telephone number of the driver","type":"string","rdfType":"http://www.w3.org/2001/XMLSchema#string","dwSourceId":"phone"}]},"path":"data/driver.csv","format":"csv"},{"name":"shipment","schema":{"fields":[{"name":"ship_id","title":"ship_id","description":"Unique identifier of the shippment","type":"integer","rdfType":"http://www.w3.org/2001/XMLSchema#integer","dwSourceId":"ship_id"},{"name":"cust_id","title":"cust_id","description":"A reference to the customer table that indicates which customer the shipment is for","type":"integer","rdfType":"http://www.w3.org/2001/XMLSchema#integer","dwSourceId":"cust_id"},{"name":"weight","title":"weight","description":"The number of pounds being transported on the shipment","type":"number","rdfType":"http://www.w3.org/2001/XMLSchema#decimal","dwSourceId":"weight"},{"name":"truck_id","title":"truck_id","description":"A reference to the trucc table that indicates which truck is used in the shipment","type":"integer","rdfType":"http://www.w3.org/2001/XMLSchema#integer","dwSourceId":"truck_id"},{"name":"driver_id","title":"driver_id","description":"A reference to the driver table that indicates which driver transported the goods in the shipment","type":"integer","rdfType":"http://www.w3.org/2001/XMLSchema#integer","dwSourceId":"driver_id"},{"name":"city_id","title":"city_id","description":"A reference to the city table that indicates the destination of the shipment","type":"integer","rdfType":"http://www.w3.org/2001/XMLSchema#integer","dwSourceId":"city_id"},{"name":"ship_date","title":"ship_date","description":"the date the the items were received by the driver","type":"date","rdfType":"http://www.w3.org/2001/XMLSchema#date","dwSourceId":"ship_date"}]},"path":"data/shipment.csv","format":"csv"},{"name":"truck","schema":{"fields":[{"name":"truck_id","title":"truck_id","description":"Unique identifier of the truck table","type":"integer","rdfType":"http://www.w3.org/2001/XMLSchema#integer","dwSourceId":"truck_id"},{"name":"make","title":"make","description":"The brand of the truck","type":"string","rdfType":"http://www.w3.org/2001/XMLSchema#string","dwSourceId":"make"},{"name":"model_year","title":"model_year","description":"The  year the truck was manufactured","type":"gyear","rdfType":"http://www.w3.org/2001/XMLSchema#gYear","dwSourceId":"model_year"}]},"path":"data/truck.csv","format":"csv"},{"name":"original/city","path":"original/city","format":"","mediatype":"text/csv","bytes":24537},{"name":"original/customer","path":"original/customer","format":"","mediatype":"text/csv","bytes":11983},{"name":"original/driver","path":"original/driver","format":"","mediatype":"text/csv","bytes":963},{"name":"original/shipment","path":"original/shipment","format":"","mediatype":"text/csv","bytes":39679},{"name":"original/truck","path":"original/truck","format":"","mediatype":"text/csv","bytes":247}]}